odoo/addons/web_button_visibility/README.rst
odoo/addons/web_button_visibility/__init__.py
odoo/addons/web_button_visibility/__manifest__.py
odoo/addons/web_button_visibility/data/demo.xml
odoo/addons/web_button_visibility/i18n/fr.po
odoo/addons/web_button_visibility/i18n/fr_CA.po
odoo/addons/web_button_visibility/i18n/it.po
odoo/addons/web_button_visibility/i18n/web_button_visibility.pot
odoo/addons/web_button_visibility/models/__init__.py
odoo/addons/web_button_visibility/models/base.py
odoo/addons/web_button_visibility/models/hide_button_rule.py
odoo/addons/web_button_visibility/models/ir_model.py
odoo/addons/web_button_visibility/readme/CONTEXT.rst
odoo/addons/web_button_visibility/readme/CONTRIBUTORS.rst
odoo/addons/web_button_visibility/readme/DESCRIPTION.rst
odoo/addons/web_button_visibility/readme/USAGE.rst
odoo/addons/web_button_visibility/security/ir.model.access.csv
odoo/addons/web_button_visibility/static/description/icon.png
odoo/addons/web_button_visibility/static/description/index.html
odoo/addons/web_button_visibility/tests/__init__.py
odoo/addons/web_button_visibility/tests/test_button_invisible.py
odoo/addons/web_button_visibility/views/views.xml
odoo14_addon_web_button_visibility-14.0.1.1.0.dist-info/METADATA
odoo14_addon_web_button_visibility-14.0.1.1.0.dist-info/WHEEL
odoo14_addon_web_button_visibility-14.0.1.1.0.dist-info/top_level.txt
odoo14_addon_web_button_visibility-14.0.1.1.0.dist-info/RECORD
